pyspssio/__init__.py
pyspssio/_version.py
pyspssio/command_line.py
pyspssio/config.py
pyspssio/constants.py
pyspssio/constants_map.py
pyspssio/errors.py
pyspssio/header.py
pyspssio/reader.py
pyspssio/spssfile.py
pyspssio/user_functions.py
pyspssio/writer.py
pyspssio/spssio/document/Input-Output Module.pdf
pyspssio/spssio/include/spssdio.h
pyspssio/spssio/include/spssdiocodes.h
pyspssio/spssio/license/LA_cs
pyspssio/spssio/license/LA_de
pyspssio/spssio/license/LA_el
pyspssio/spssio/license/LA_en
pyspssio/spssio/license/LA_es
pyspssio/spssio/license/LA_fr
pyspssio/spssio/license/LA_in
pyspssio/spssio/license/LA_it
pyspssio/spssio/license/LA_ja
pyspssio/spssio/license/LA_ko
pyspssio/spssio/license/LA_lt
pyspssio/spssio/license/LA_pl
pyspssio/spssio/license/LA_pt
pyspssio/spssio/license/LA_ru
pyspssio/spssio/license/LA_sl
pyspssio/spssio/license/LA_tr
pyspssio/spssio/license/LA_zh
pyspssio/spssio/license/LA_zh_TW
pyspssio/spssio/license/REDIST
pyspssio/spssio/license/notices
pyspssio/spssio/lin64/libgsk8iccs_64.so
pyspssio/spssio/lin64/libicudata.so.61
pyspssio/spssio/lin64/libicudata.so.61.2
pyspssio/spssio/lin64/libicui18n.so.61
pyspssio/spssio/lin64/libicui18n.so.61.2
pyspssio/spssio/lin64/libicuuc.so.61
pyspssio/spssio/lin64/libicuuc.so.61.2
pyspssio/spssio/lin64/libspssdio.so.1
pyspssio/spssio/lin64/libspssjdio.so.1
pyspssio/spssio/lin64/libzlib1213spss.so
pyspssio/spssio/macos/libgsk8iccs.dylib
pyspssio/spssio/macos/libicudata.61.2.dylib
pyspssio/spssio/macos/libicui18n.61.2.dylib
pyspssio/spssio/macos/libicuuc.61.2.dylib
pyspssio/spssio/macos/libspssdio.dylib
pyspssio/spssio/macos/libspssjdio.dylib
pyspssio/spssio/macos/libzlib1213spss.dylib
pyspssio/spssio/win64/gsk8iccs_64.dll
pyspssio/spssio/win64/icudt61.dll
pyspssio/spssio/win64/icuin61.dll
pyspssio/spssio/win64/icuuc61.dll
pyspssio/spssio/win64/msvcp120.dll
pyspssio/spssio/win64/msvcr120.dll
pyspssio/spssio/win64/spssdio.vb
pyspssio/spssio/win64/spssio64.dll
pyspssio/spssio/win64/spssio64.lib
pyspssio-0.5.0.dist-info/LICENSE.txt
pyspssio-0.5.0.dist-info/METADATA
pyspssio-0.5.0.dist-info/WHEEL
pyspssio-0.5.0.dist-info/entry_points.txt
pyspssio-0.5.0.dist-info/top_level.txt
pyspssio-0.5.0.dist-info/RECORD
