Metadata-Version: 2.1
Name: pyspssio
Version: 0.5.0
Summary: Read and write SPSS (.sav and .zsav) files to/from pandas dataframes
Home-page: https://github.com/stspec/pyspssio
Author: Steven Spector
Author-email: stspec.dev@gmail.com
License: MIT
Project-URL: Documentation, https://pyspssio.readthedocs.io
Requires-Python: >=3.6
License-File: LICENSE.txt
Requires-Dist: pandas
Requires-Dist: psutil
